fsqlexec/SQLFileExecutor.py
fsqlexec/__init__.py
fsqlexec/command.py
fsqlexec/fsqlexec.py
fsqlexec-0.2.12.dist-info/LICENSE.txt
fsqlexec-0.2.12.dist-info/METADATA
fsqlexec-0.2.12.dist-info/WHEEL
fsqlexec-0.2.12.dist-info/entry_points.txt
fsqlexec-0.2.12.dist-info/top_level.txt
fsqlexec-0.2.12.dist-info/RECORD
