Metadata-Version: 2.1
Name: fsqlexec
Version: 0.2.12
Summary: SQLファイルからSQLをまとめて実行する
Home-page: https://github.com/karakawa88/SQLFileExecutor
Author: Kentarou Arakawa
Author-email: kagalpan@kacpp.xyz
License: UNKNOWN
Platform: UNKNOWN
Classifier: License :: OSI Approved :: MIT License
Classifier: Programming Language :: Python :: 3
Classifier: Programming Language :: Python :: 3.6
Classifier: Programming Language :: Python :: 3.7
Classifier: Programming Language :: Python :: 3.8
Classifier: Programming Language :: Python :: 3.9
Classifier: Operating System :: OS Independent
Requires-Python: ~=3.9
Requires-Dist: psycopg2 (>=2.*)
Requires-Dist: libpyka (>=0.*)
Requires-Dist: requests (>=2.*)
Requires-Dist: click (>=8.*)
